odoo/addons/stock_account_no_auto_reconcile/README.rst
odoo/addons/stock_account_no_auto_reconcile/__init__.py
odoo/addons/stock_account_no_auto_reconcile/__manifest__.py
odoo/addons/stock_account_no_auto_reconcile/i18n/es.po
odoo/addons/stock_account_no_auto_reconcile/i18n/stock_account_no_auto_reconcile.pot
odoo/addons/stock_account_no_auto_reconcile/models/__init__.py
odoo/addons/stock_account_no_auto_reconcile/models/account_move.py
odoo/addons/stock_account_no_auto_reconcile/models/company.py
odoo/addons/stock_account_no_auto_reconcile/models/res_config_settings.py
odoo/addons/stock_account_no_auto_reconcile/readme/CONTRIBUTORS.rst
odoo/addons/stock_account_no_auto_reconcile/readme/DESCRIPTION.rst
odoo/addons/stock_account_no_auto_reconcile/readme/USAGE.rst
odoo/addons/stock_account_no_auto_reconcile/static/description/icon.png
odoo/addons/stock_account_no_auto_reconcile/static/description/index.html
odoo/addons/stock_account_no_auto_reconcile/tests/__init__.py
odoo/addons/stock_account_no_auto_reconcile/tests/test_account_no_auto_reconcile.py
odoo/addons/stock_account_no_auto_reconcile/views/res_config_settings_views.xml
odoo_addon_stock_account_no_auto_reconcile-15.0.1.0.0.4.dist-info/METADATA
odoo_addon_stock_account_no_auto_reconcile-15.0.1.0.0.4.dist-info/WHEEL
odoo_addon_stock_account_no_auto_reconcile-15.0.1.0.0.4.dist-info/top_level.txt
odoo_addon_stock_account_no_auto_reconcile-15.0.1.0.0.4.dist-info/RECORD
