Metadata-Version: 2.1
Name: odoo-addon-stock-account-no-auto-reconcile
Version: 15.0.1.0.0.4
Summary: Do not try to reconcile stock interim related JE
Home-page: https://github.com/OCA/account-financial-tools
Author: Odoo Community Association (OCA), ForgeFlow,
Author-email: support@odoo-community.org
License: AGPL-3
Platform: UNKNOWN
Classifier: Programming Language :: Python
Classifier: Framework :: Odoo
Classifier: Framework :: Odoo :: 15.0
Classifier: License :: OSI Approved :: GNU Affero General Public License v3
Requires-Python: >=3.8
Requires-Dist: odoo <15.1dev,>=15.0a
